repeatexec/__init__.py
repeatexec/__main__.py
repeatexec/gitutil.py
repeatexec/repeatexec.py
repeatexec-0.0.7.dist-info/METADATA
repeatexec-0.0.7.dist-info/WHEEL
repeatexec-0.0.7.dist-info/entry_points.txt
repeatexec-0.0.7.dist-info/top_level.txt
repeatexec-0.0.7.dist-info/RECORD
